setup.py
monkeys/__init__.py
monkeys/aco.py
monkeys/asts.py
monkeys/exceptions.py
monkeys/search.py
monkeys/trees.py
monkeys/typing.py
monkeys.egg-info/PKG-INFO
monkeys.egg-info/SOURCES.txt
monkeys.egg-info/dependency_links.txt
monkeys.egg-info/requires.txt
monkeys.egg-info/top_level.txt
monkeys/common/__init__.py
monkeys/common/numeric.py
monkeys/common/xpath.py
monkeys/tools/__init__.py
monkeys/tools/diagnostics.py
monkeys/tools/display.py
monkeys/tools/wrench.py