Metadata-Version: 1.1
Name: monkeys
Version: 0.0.15
Summary: A strongly-typed genetic programming framework
Home-page: https://github.com/hchasestevens/monkeys
Author: H. Chase Stevens
Author-email: chase@chasestevens.com
License: MIT
Keywords: genetic programming optimization
Platform: UNKNOWN
Classifier: Development Status :: 3 - Alpha
Classifier: Programming Language :: Python
Classifier: Programming Language :: Python :: 2
Classifier: Programming Language :: Python :: 2.7
Classifier: Programming Language :: Python :: 3
Classifier: Programming Language :: Python :: 3.6
Classifier: Intended Audience :: Developers
Classifier: Operating System :: OS Independent
Classifier: License :: OSI Approved :: MIT License
Classifier: Natural Language :: English
